pai_soma_data/__init__.py
pai_soma_data/pai_soma_data.py
pai_soma_data-1.0.3.dist-info/METADATA
pai_soma_data-1.0.3.dist-info/WHEEL
pai_soma_data-1.0.3.dist-info/top_level.txt
pai_soma_data-1.0.3.dist-info/RECORD
