Metadata-Version: 2.1
Name: pai_soma_data
Version: 1.0.3
Summary: A class to handle data from a Soma experiment made by Phenomic AI
Author-email: Phenomic AI <sctx@phenomic.ai>
License: MIT
Classifier: Development Status :: 4 - Beta
Classifier: Intended Audience :: Developers
Classifier: Intended Audience :: Information Technology
Classifier: Intended Audience :: Science/Research
Classifier: Programming Language :: Python
Classifier: Topic :: Scientific/Engineering :: Bio-Informatics
Classifier: Operating System :: POSIX :: Linux
Classifier: Operating System :: MacOS :: MacOS X
Classifier: Programming Language :: Python :: 3.10
Classifier: Programming Language :: Python :: 3.11
Requires-Python: <3.12,>=3.8
Requires-Dist: tiledbsoma
